[
  {
    "version": "6.05",
    "region": "Global",
    "lists": {
      "ServerZoneIpcType": [
        {
          "name": "AirshipTimers",
          "opcode": 151
        },
        {
          "name": "AirshipExplorationResult",
          "opcode": 646
        },
        {
          "name": "ActorControlSelf",
          "opcode": 395
        },
        {
          "name": "ActorMove",
          "opcode": 743
        },
        {
          "name": "ActorControl",
          "opcode": 453
        },
        {
          "name": "ActorGauge",
          "opcode": 848
        },
        {
          "name": "ActorSetPos",
          "opcode": 274
        },
        {
          "name": "AirshipStatusList",
          "opcode": 864
        },
        {
          "name": "ActorCast",
          "opcode": 481
        },
        {
          "name": "ActorControlTarget",
          "opcode": 911
        },
        {
          "name": "AirshipStatus",
          "opcode": 922
        },
        {
          "name": "ContainerInfo",
          "opcode": 241
        },
        {
          "name": "CFNotify",
          "opcode": 319
        },
        {
          "name": "CraftingLog",
          "opcode": 166
        },
        {
          "name": "CurrencyCrystalInfo",
          "opcode": 947
        },
        {
          "name": "DesynthResult",
          "opcode": 851
        },
        {
          "name": "EventPlay16",
          "opcode": 769
        },
        {
          "name": "EffectResultBasic",
          "opcode": 762
        },
        {
          "name": "EventPlay4",
          "opcode": 925
        },
        {
          "name": "EventPlay64",
          "opcode": 711
        },
        {
          "name": "EventStart",
          "opcode": 693
        },
        {
          "name": "EventPlay",
          "opcode": 518
        },
        {
          "name": "EventFinish",
          "opcode": 489
        },
        {
          "name": "EventPlay8",
          "opcode": 879
        },
        {
          "name": "Examine",
          "opcode": 829
        },
        {
          "name": "ExamineSearchInfo",
          "opcode": 567
        },
        {
          "name": "EventPlay32",
          "opcode": 250
        },
        {
          "name": "Effect",
          "opcode": 409
        },
        {
          "name": "EventPlay128",
          "opcode": 474
        },
        {
          "name": "EnvironmentControl",
          "opcode": 332
        },
        {
          "name": "EventPlay255",
          "opcode": 345
        },
        {
          "name": "EffectResult",
          "opcode": 399
        },
        {
          "name": "FreeCompanyInfo",
          "opcode": 458
        },
        {
          "name": "FreeCompanyDialog",
          "opcode": 556
        },
        {
          "name": "GatheringLog",
          "opcode": 644
        },
        {
          "name": "ItemInfo",
          "opcode": 896
        },
        {
          "name": "ItemMarketBoardInfo",
          "opcode": 260
        },
        {
          "name": "InventoryTransactionFinish",
          "opcode": 830
        },
        {
          "name": "IslandWorkshopSupplyDemand",
          "opcode": 767
        },
        {
          "name": "InventoryActionAck",
          "opcode": 999
        },
        {
          "name": "InitZone",
          "opcode": 583
        },
        {
          "name": "InventoryTransaction",
          "opcode": 651
        },
        {
          "name": "Logout",
          "opcode": 772
        },
        {
          "name": "MarketBoardItemListingHistory",
          "opcode": 418
        },
        {
          "name": "MarketBoardPurchase",
          "opcode": 549
        },
        {
          "name": "MarketBoardSearchResult",
          "opcode": 559
        },
        {
          "name": "MarketBoardItemListing",
          "opcode": 785
        },
        {
          "name": "MarketBoardItemListingCount",
          "opcode": 492
        },
        {
          "name": "NpcSpawn",
          "opcode": 931
        },
        {
          "name": "ObjectSpawn",
          "opcode": 310
        },
        {
          "name": "PrepareZoning",
          "opcode": 333
        },
        {
          "name": "PlayerSetup",
          "opcode": 877
        },
        {
          "name": "PlayerSpawn",
          "opcode": 298
        },
        {
          "name": "PlaceFieldMarkerPreset",
          "opcode": 519
        },
        {
          "name": "PlaceFieldMarker",
          "opcode": 283
        },
        {
          "name": "Playtime",
          "opcode": 951
        },
        {
          "name": "PlayerStats",
          "opcode": 953
        },
        {
          "name": "RetainerInformation",
          "opcode": 212
        },
        {
          "name": "ResultDialog",
          "opcode": 154
        },
        {
          "name": "StatusEffectList3",
          "opcode": 921
        },
        {
          "name": "SubmarineProgressionStatus",
          "opcode": 854
        },
        {
          "name": "SubmarineStatusList",
          "opcode": 872
        },
        {
          "name": "SystemLogMessage",
          "opcode": 268
        },
        {
          "name": "StatusEffectList",
          "opcode": 713
        },
        {
          "name": "SubmarineTimers",
          "opcode": 698
        },
        {
          "name": "StatusEffectList2",
          "opcode": 513
        },
        {
          "name": "SubmarineExplorationResult",
          "opcode": 363
        },
        {
          "name": "UpdateSearchInfo",
          "opcode": 897
        },
        {
          "name": "UpdateClassInfo",
          "opcode": 248
        },
        {
          "name": "UpdateHpMpTp",
          "opcode": 270
        },
        {
          "name": "UpdateInventorySlot",
          "opcode": 980
        },
        {
          "name": "WeatherChange",
          "opcode": 797
        }
      ],
      "ClientZoneIpcType": [
        {
          "name": "InventoryModifyHandler",
          "opcode": 227
        },
        {
          "name": "MarketBoardPurchaseHandler",
          "opcode": 981
        },
        {
          "name": "SetSearchInfoHandler",
          "opcode": 800
        },
        {
          "name": "UpdatePositionHandler",
          "opcode": 680
        }
      ],
      "ServerLobbyIpcType": [
        {
          "name": "LobbyError",
          "opcode": 2
        },
        {
          "name": "LobbyServiceAccountList",
          "opcode": 12
        },
        {
          "name": "LobbyCharList",
          "opcode": 13
        },
        {
          "name": "LobbyCharCreate",
          "opcode": 14
        },
        {
          "name": "LobbyEnterWorld",
          "opcode": 15
        },
        {
          "name": "LobbyServerList",
          "opcode": 21
        },
        {
          "name": "LobbyRetainerList",
          "opcode": 23
        }
      ],
      "ClientLobbyIpcType": [
        {
          "name": "ClientVersionInfo",
          "opcode": 5
        },
        {
          "name": "ReqCharList",
          "opcode": 3
        },
        {
          "name": "ReqEnterWorld",
          "opcode": 4
        },
        {
          "name": "ReqCharDelete",
          "opcode": 10
        },
        {
          "name": "ReqCharCreate",
          "opcode": 11
        }
      ],
      "ServerChatIpcType": [],
      "ClientChatIpcType": []
    }
  },
  {
    "version": "7.05",
    "region": "CN",
    "lists": {
      "ServerZoneIpcType": [
        {
          "name": "AirshipTimers",
          "opcode": 105
        },
        {
          "name": "AirshipStatus",
          "opcode": 767
        },
        {
          "name": "AoeEffect8",
          "opcode": 774
        },
        {
          "name": "AoeEffect32",
          "opcode": 204
        },
        {
          "name": "ActorGauge",
          "opcode": 642
        },
        {
          "name": "ActorControlTarget",
          "opcode": 672
        },
        {
          "name": "AirshipStatusList",
          "opcode": 268
        },
        {
          "name": "ActorSetPos",
          "opcode": 943
        },
        {
          "name": "ActorCast",
          "opcode": 956
        },
        {
          "name": "ActorControl",
          "opcode": 132
        },
        {
          "name": "AoeEffect24",
          "opcode": 361
        },
        {
          "name": "ActorControlSelf",
          "opcode": 123
        },
        {
          "name": "AirshipExplorationResult",
          "opcode": 614
        },
        {
          "name": "ActorMove",
          "opcode": 635
        },
        {
          "name": "AoeEffect16",
          "opcode": 377
        },
        {
          "name": "BattleTalk2",
          "opcode": 294
        },
        {
          "name": "BossStatusEffectList",
          "opcode": 877
        },
        {
          "name": "ContainerInfo",
          "opcode": 702
        },
        {
          "name": "CEDirector",
          "opcode": 437
        },
        {
          "name": "CFPreferredRole",
          "opcode": 167
        },
        {
          "name": "Countdown",
          "opcode": 142
        },
        {
          "name": "CFNotify",
          "opcode": 125
        },
        {
          "name": "CountdownCancel",
          "opcode": 399
        },
        {
          "name": "CurrencyCrystalInfo",
          "opcode": 686
        },
        {
          "name": "DesynthResult",
          "opcode": 291
        },
        {
          "name": "EventStart",
          "opcode": 699
        },
        {
          "name": "EventPlay4",
          "opcode": 991
        },
        {
          "name": "EventFinish",
          "opcode": 764
        },
        {
          "name": "EventPlay32",
          "opcode": 198
        },
        {
          "name": "Effect",
          "opcode": 829
        },
        {
          "name": "EventPlay",
          "opcode": 636
        },
        {
          "name": "Examine",
          "opcode": 150
        },
        {
          "name": "ExamineSearchInfo",
          "opcode": 957
        },
        {
          "name": "EnvironmentControl",
          "opcode": 474
        },
        {
          "name": "EffectResult",
          "opcode": 687
        },
        {
          "name": "FreeCompanyDialog",
          "opcode": 647
        },
        {
          "name": "FateInfo",
          "opcode": 578
        },
        {
          "name": "FreeCompanyInfo",
          "opcode": 992
        },
        {
          "name": "HousingWardInfo",
          "opcode": 468
        },
        {
          "name": "IslandWorkshopSupplyDemand",
          "opcode": 736
        },
        {
          "name": "InventoryTransaction",
          "opcode": 115
        },
        {
          "name": "ItemMarketBoardInfo",
          "opcode": 296
        },
        {
          "name": "ItemInfo",
          "opcode": 470
        },
        {
          "name": "InventoryTransactionFinish",
          "opcode": 171
        },
        {
          "name": "InventoryActionAck",
          "opcode": 646
        },
        {
          "name": "InitZone",
          "opcode": 791
        },
        {
          "name": "Logout",
          "opcode": 483
        },
        {
          "name": "MarketBoardPurchase",
          "opcode": 334
        },
        {
          "name": "MarketBoardItemListingCount",
          "opcode": 639
        },
        {
          "name": "MarketBoardItemListing",
          "opcode": 796
        },
        {
          "name": "MarketBoardItemListingHistory",
          "opcode": 223
        },
        {
          "name": "MiniCactpotInit",
          "opcode": 345
        },
        {
          "name": "MarketBoardSearchResult",
          "opcode": 657
        },
        {
          "name": "NpcSpawn2",
          "opcode": 645
        },
        {
          "name": "NpcSpawn",
          "opcode": 164
        },
        {
          "name": "NpcYell",
          "opcode": 720
        },
        {
          "name": "ObjectSpawn",
          "opcode": 139
        },
        {
          "name": "PlayerStats",
          "opcode": 289
        },
        {
          "name": "PlaceFieldMarker",
          "opcode": 778
        },
        {
          "name": "PlayerSetup",
          "opcode": 519
        },
        {
          "name": "PlayerSpawn",
          "opcode": 293
        },
        {
          "name": "PlaceFieldMarkerPreset",
          "opcode": 590
        },
        {
          "name": "PrepareZoning",
          "opcode": 653
        },
        {
          "name": "Playtime",
          "opcode": 545
        },
        {
          "name": "RSV",
          "opcode": 858
        },
        {
          "name": "RetainerInformation",
          "opcode": 825
        },
        {
          "name": "SubmarineTimers",
          "opcode": 740
        },
        {
          "name": "SubmarineStatusList",
          "opcode": 962
        },
        {
          "name": "SystemLogMessage",
          "opcode": 163
        },
        {
          "name": "SubmarineProgressionStatus",
          "opcode": 629
        },
        {
          "name": "SubmarineExplorationResult",
          "opcode": 445
        },
        {
          "name": "StatusEffectList",
          "opcode": 219
        },
        {
          "name": "StatusEffectList3",
          "opcode": 415
        },
        {
          "name": "StatusEffectList2",
          "opcode": 582
        },
        {
          "name": "UpdateHpMpTp",
          "opcode": 343
        },
        {
          "name": "UpdateInventorySlot",
          "opcode": 613
        },
        {
          "name": "UpdateSearchInfo",
          "opcode": 341
        },
        {
          "name": "UpdateClassInfo",
          "opcode": 752
        },
        {
          "name": "WeatherChange",
          "opcode": 890
        }
      ],
      "ClientZoneIpcType": [
        {
          "name": "ChatHandler",
          "opcode": 274
        },
        {
          "name": "ClientTrigger",
          "opcode": 647
        },
        {
          "name": "InventoryModifyHandler",
          "opcode": 431
        },
        {
          "name": "MarketBoardPurchaseHandler",
          "opcode": 858
        },
        {
          "name": "MarketBoardRequestItemListingInfo",
          "opcode": 896
        },
        {
          "name": "SetSearchInfoHandler",
          "opcode": 955
        },
        {
          "name": "UpdatePositionInstance",
          "opcode": 164
        },
        {
          "name": "UpdatePositionHandler",
          "opcode": 433
        }
      ],
      "ServerLobbyIpcType": [],
      "ClientLobbyIpcType": [],
      "ServerChatIpcType": [],
      "ClientChatIpcType": []
    }
  },
  {
    "version": "7.0",
    "region": "KR",
    "lists": {
      "ServerZoneIpcType": [
        {
          "name": "ActorSetPos",
          "opcode": 114
        },
        {
          "name": "ActorGauge",
          "opcode": 447
        },
        {
          "name": "AirshipTimers",
          "opcode": 477
        },
        {
          "name": "AirshipExplorationResult",
          "opcode": 592
        },
        {
          "name": "AoeEffect8",
          "opcode": 411
        },
        {
          "name": "ActorCast",
          "opcode": 385
        },
        {
          "name": "AoeEffect24",
          "opcode": 376
        },
        {
          "name": "AoeEffect32",
          "opcode": 642
        },
        {
          "name": "ActorControlSelf",
          "opcode": 652
        },
        {
          "name": "ActorMove",
          "opcode": 670
        },
        {
          "name": "ActorControlTarget",
          "opcode": 751
        },
        {
          "name": "AirshipStatusList",
          "opcode": 467
        },
        {
          "name": "AirshipStatus",
          "opcode": 949
        },
        {
          "name": "AoeEffect16",
          "opcode": 134
        },
        {
          "name": "ActorControl",
          "opcode": 900
        },
        {
          "name": "CurrencyCrystalInfo",
          "opcode": 820
        },
        {
          "name": "ContainerInfo",
          "opcode": 424
        },
        {
          "name": "CFNotify",
          "opcode": 749
        },
        {
          "name": "CFPreferredRole",
          "opcode": 960
        },
        {
          "name": "CEDirector",
          "opcode": 889
        },
        {
          "name": "DesynthResult",
          "opcode": 967
        },
        {
          "name": "DespawnCharacter",
          "opcode": 218
        },
        {
          "name": "EventPlay4",
          "opcode": 936
        },
        {
          "name": "EffectResult8",
          "opcode": 705
        },
        {
          "name": "EffectResultBasic16",
          "opcode": 956
        },
        {
          "name": "ExamineFreeCompanyInfo",
          "opcode": 731
        },
        {
          "name": "EffectResultBasic32",
          "opcode": 629
        },
        {
          "name": "EffectResult32",
          "opcode": 962
        },
        {
          "name": "EventPlay64",
          "opcode": 475
        },
        {
          "name": "Effect",
          "opcode": 892
        },
        {
          "name": "EffectResultBasic4",
          "opcode": 506
        },
        {
          "name": "EffectResult",
          "opcode": 496
        },
        {
          "name": "EventPlay",
          "opcode": 765
        },
        {
          "name": "EventPlay8",
          "opcode": 971
        },
        {
          "name": "EnvironmentControl",
          "opcode": 688
        },
        {
          "name": "EventStart",
          "opcode": 738
        },
        {
          "name": "EventPlay128",
          "opcode": 584
        },
        {
          "name": "EffectResult4",
          "opcode": 370
        },
        {
          "name": "EventPlay255",
          "opcode": 256
        },
        {
          "name": "ExamineSearchInfo",
          "opcode": 268
        },
        {
          "name": "EventFinish",
          "opcode": 324
        },
        {
          "name": "EffectResultBasic8",
          "opcode": 188
        },
        {
          "name": "EffectResultBasic64",
          "opcode": 155
        },
        {
          "name": "EventPlay16",
          "opcode": 141
        },
        {
          "name": "EffectResult16",
          "opcode": 215
        },
        {
          "name": "EventPlay32",
          "opcode": 438
        },
        {
          "name": "EffectResultBasic",
          "opcode": 441
        },
        {
          "name": "FreeCompanyDialog",
          "opcode": 336
        },
        {
          "name": "FreeCompanyInfo",
          "opcode": 752
        },
        {
          "name": "FirstAttack",
          "opcode": 479
        },
        {
          "name": "HousingWardInfo",
          "opcode": 803
        },
        {
          "name": "IslandWorkshopSupplyDemand",
          "opcode": 685
        },
        {
          "name": "InitZone",
          "opcode": 302
        },
        {
          "name": "InventoryTransaction",
          "opcode": 327
        },
        {
          "name": "ItemInfo",
          "opcode": 169
        },
        {
          "name": "ItemMarketBoardInfo",
          "opcode": 579
        },
        {
          "name": "InventoryTransactionFinish",
          "opcode": 539
        },
        {
          "name": "InventoryActionAck",
          "opcode": 968
        },
        {
          "name": "Logout",
          "opcode": 619
        },
        {
          "name": "MarketBoardItemListingHistory",
          "opcode": 432
        },
        {
          "name": "MiniCactpotInit",
          "opcode": 537
        },
        {
          "name": "MarketBoardItemListing",
          "opcode": 982
        },
        {
          "name": "MarketBoardPurchase",
          "opcode": 898
        },
        {
          "name": "MarketBoardItemListingCount",
          "opcode": 669
        },
        {
          "name": "MarketBoardSearchResult",
          "opcode": 804
        },
        {
          "name": "NpcSpawn",
          "opcode": 813
        },
        {
          "name": "NpcSpawn2",
          "opcode": 703
        },
        {
          "name": "ObjectSpawn",
          "opcode": 119
        },
        {
          "name": "PlayerSetup",
          "opcode": 333
        },
        {
          "name": "PlaceFieldMarker",
          "opcode": 653
        },
        {
          "name": "PlayerStats",
          "opcode": 290
        },
        {
          "name": "Playtime",
          "opcode": 270
        },
        {
          "name": "PlayerSpawn",
          "opcode": 647
        },
        {
          "name": "PlaceFieldMarkerPreset",
          "opcode": 462
        },
        {
          "name": "PrepareZoning",
          "opcode": 459
        },
        {
          "name": "RetainerInformation",
          "opcode": 198
        },
        {
          "name": "StatusEffectListPlayerDouble",
          "opcode": 974
        },
        {
          "name": "SystemLogMessage16",
          "opcode": 199
        },
        {
          "name": "StatusEffectListDouble",
          "opcode": 939
        },
        {
          "name": "StatusEffectListPlayer",
          "opcode": 942
        },
        {
          "name": "SystemLogMessage2",
          "opcode": 177
        },
        {
          "name": "SubmarineExplorationResult",
          "opcode": 160
        },
        {
          "name": "SubmarineStatusList",
          "opcode": 723
        },
        {
          "name": "StatusEffectList",
          "opcode": 633
        },
        {
          "name": "StatusEffectListEureka",
          "opcode": 622
        },
        {
          "name": "SystemLogMessage",
          "opcode": 595
        },
        {
          "name": "SystemLogMessage4",
          "opcode": 418
        },
        {
          "name": "SubmarineProgressionStatus",
          "opcode": 576
        },
        {
          "name": "SocialList",
          "opcode": 562
        },
        {
          "name": "SubmarineTimers",
          "opcode": 552
        },
        {
          "name": "SystemLogMessage8",
          "opcode": 551
        },
        {
          "name": "StatusEffectListBozja",
          "opcode": 857
        },
        {
          "name": "UpdateClassInfoEureka",
          "opcode": 741
        },
        {
          "name": "UpdateClassInfo",
          "opcode": 733
        },
        {
          "name": "UpdateClassInfoBozja",
          "opcode": 919
        },
        {
          "name": "UpdateSearchInfo",
          "opcode": 373
        },
        {
          "name": "UpdateInventorySlot",
          "opcode": 390
        },
        {
          "name": "UpdateHpMpTp",
          "opcode": 986
        },
        {
          "name": "WeatherChange",
          "opcode": 616
        }
      ],
      "ClientZoneIpcType": [
        {
          "name": "ActionRequestGroundTargeted",
          "opcode": 495
        },
        {
          "name": "ActionRequest",
          "opcode": 938
        },
        {
          "name": "ClientTrigger",
          "opcode": 336
        },
        {
          "name": "ClientCountdownInitiate",
          "opcode": 525
        },
        {
          "name": "ChatHandler",
          "opcode": 583
        },
        {
          "name": "InventoryModifyHandler",
          "opcode": 344
        },
        {
          "name": "LogoutHandler",
          "opcode": 400
        },
        {
          "name": "MarketBoardPurchaseHandler",
          "opcode": 269
        },
        {
          "name": "SetSearchInfoHandler",
          "opcode": 659
        },
        {
          "name": "UpdatePositionInstance",
          "opcode": 813
        },
        {
          "name": "UpdatePositionHandler",
          "opcode": 980
        }
      ],
      "ServerLobbyIpcType": [
        {
          "name": "LobbyError",
          "opcode": 2
        },
        {
          "name": "LobbyServiceAccountList",
          "opcode": 12
        },
        {
          "name": "LobbyCharList",
          "opcode": 13
        },
        {
          "name": "LobbyCharCreate",
          "opcode": 14
        },
        {
          "name": "LobbyEnterWorld",
          "opcode": 15
        },
        {
          "name": "LobbyServerList",
          "opcode": 21
        },
        {
          "name": "LobbyRetainerList",
          "opcode": 23
        }
      ],
      "ClientLobbyIpcType": [
        {
          "name": "ClientVersionInfo",
          "opcode": 5
        },
        {
          "name": "ReqCharList",
          "opcode": 3
        },
        {
          "name": "ReqEnterWorld",
          "opcode": 4
        },
        {
          "name": "ReqCharDelete",
          "opcode": 10
        },
        {
          "name": "ReqCharCreate",
          "opcode": 11
        }
      ],
      "ServerChatIpcType": [],
      "ClientChatIpcType": []
    }
  }
]